{
  "song_title": "From the start",
  "writer": "Frith Hilton",
  "release_date": "July 2, 2022",
  "cover": "https://frithhilton.com.ng/musicpool/covers/5/92.jpg",
  "mp3_url": "https://frithhilton.com.ng/mp3/5/1.) From the start.mp3",
  "duration": 186.64489795918368,
  "id": "92",
  "lyrics": [
    {
      "line": "[Intro]",
      "annotations": {},
      "timestamp": "0"
    },
    {
      "line": "Am ’bout to get it right now",
      "annotations": {},
      "timestamp": "0"
    },
    {
      "line": "Got the reelers out",
      "annotations": {},
      "timestamp": "0"
    },
    {
      "line": "This ain’t no comeback",
      "annotations": {},
      "timestamp": "0"
    },
    {
      "line": "Got the realest out",
      "annotations": {},
      "timestamp": "0"
    },
    {
      "line": "Winning jones",
      "annotations": {},
      "timestamp": "0"
    },
    {
      "line": "",
      "annotations": {},
      "timestamp": "0"
    },
    {
      "line": "[Verse 1]",
      "annotations": {},
      "timestamp": "0"
    },
    {
      "line": "Soothing prose",
      "annotations": {},
      "timestamp": "0"
    },
    {
      "line": "Had some of those",
      "annotations": {},
      "timestamp": "0"
    },
    {
      "line": "How it feels when you’re hitting notes",
      "annotations": {},
      "timestamp": "0"
    },
    {
      "line": "From scruffy toes",
      "annotations": {},
      "timestamp": "0"
    },
    {
      "line": "Tussle toss tuck my pickle hope",
      "annotations": {},
      "timestamp": "0"
    },
    {
      "line": "I could grow up",
      "annotations": {},
      "timestamp": "0"
    },
    {
      "line": "But my caddy hollow",
      "annotations": {},
      "timestamp": "0"
    },
    {
      "line": "Under umbrella with an ordinal",
      "annotations": {},
      "timestamp": "0"
    },
    {
      "line": "On this",
      "annotations": {},
      "timestamp": "0"
    },
    {
      "line": "Beat it! (beat it!)",
      "annotations": {},
      "timestamp": "0"
    },
    {
      "line": "Heard a call from the galley",
      "annotations": {},
      "timestamp": "0"
    },
    {
      "line": "Penchant shit",
      "annotations": {},
      "timestamp": "0"
    },
    {
      "line": "So I hit it",
      "annotations": {},
      "timestamp": "0"
    },
    {
      "line": "In the dining",
      "annotations": {},
      "timestamp": "0"
    },
    {
      "line": "Another eeny",
      "annotations": {},
      "timestamp": "0"
    },
    {
      "line": "On my hammock I’ll be reeling",
      "annotations": {},
      "timestamp": "0"
    },
    {
      "line": "Nitty gritty",
      "annotations": {},
      "timestamp": "0"
    },
    {
      "line": "Swish a titbit",
      "annotations": {},
      "timestamp": "0"
    },
    {
      "line": "Precocious I’ve been handed the garter",
      "annotations": {},
      "timestamp": "0"
    },
    {
      "line": "Hustled for a take now it all feels like banter",
      "annotations": {},
      "timestamp": "0"
    },
    {
      "line": "Banter",
      "annotations": {},
      "timestamp": "0"
    },
    {
      "line": "",
      "annotations": {},
      "timestamp": "0"
    },
    {
      "line": "[Chorus]",
      "annotations": {},
      "timestamp": "0"
    },
    {
      "line": "Am ’bout to get it right now",
      "annotations": {},
      "timestamp": "0"
    },
    {
      "line": "Got the reelers out",
      "annotations": {},
      "timestamp": "0"
    },
    {
      "line": "This ain’t no comeback",
      "annotations": {},
      "timestamp": "0"
    },
    {
      "line": "Got the realest out",
      "annotations": {},
      "timestamp": "0"
    },
    {
      "line": "Winning jones",
      "annotations": {},
      "timestamp": "0"
    },
    {
      "line": "Am ’bout to get it right now",
      "annotations": {},
      "timestamp": "0"
    },
    {
      "line": "Got the reelers out",
      "annotations": {},
      "timestamp": "0"
    },
    {
      "line": "This ain’t no comeback",
      "annotations": {},
      "timestamp": "0"
    },
    {
      "line": "Got the realest out",
      "annotations": {},
      "timestamp": "0"
    },
    {
      "line": "Winning jones",
      "annotations": {},
      "timestamp": "0"
    },
    {
      "line": "Jones",
      "annotations": {},
      "timestamp": "0"
    },
    {
      "line": "",
      "annotations": {},
      "timestamp": "0"
    },
    {
      "line": "[Verse 2]",
      "annotations": {},
      "timestamp": "0"
    },
    {
      "line": "She had a ballast had me in rough waters",
      "annotations": {},
      "timestamp": "0"
    },
    {
      "line": "On the zinc had me no drama",
      "annotations": {},
      "timestamp": "0"
    },
    {
      "line": "Joie de vivre",
      "annotations": {},
      "timestamp": "0"
    },
    {
      "line": "She’s the girl who make you burn the vista",
      "annotations": {},
      "timestamp": "0"
    },
    {
      "line": "And they say I don’t drink no alcohol? (alcohol)",
      "annotations": {},
      "timestamp": "0"
    },
    {
      "line": "But I still put the shit to work",
      "annotations": {},
      "timestamp": "0"
    },
    {
      "line": "Put in work",
      "annotations": {},
      "timestamp": "0"
    },
    {
      "line": "In the zinc had to hit her luck",
      "annotations": {},
      "timestamp": "0"
    },
    {
      "line": "No fumble mop (here’s the truth)",
      "annotations": {},
      "timestamp": "0"
    },
    {
      "line": "Come hurdle form",
      "annotations": {},
      "timestamp": "0"
    },
    {
      "line": "Another prom",
      "annotations": {},
      "timestamp": "0"
    },
    {
      "line": "Adult topping for a one way cone",
      "annotations": {},
      "timestamp": "0"
    },
    {
      "line": "",
      "annotations": {},
      "timestamp": "0"
    },
    {
      "line": "[Chorus]",
      "annotations": {},
      "timestamp": "0"
    },
    {
      "line": "Am ’bout to get it right now",
      "annotations": {},
      "timestamp": "0"
    },
    {
      "line": "Got the reelers out",
      "annotations": {},
      "timestamp": "0"
    },
    {
      "line": "This ain’t no comeback",
      "annotations": {},
      "timestamp": "0"
    },
    {
      "line": "Got the realest out",
      "annotations": {},
      "timestamp": "0"
    },
    {
      "line": "Am ’bout to get it right now",
      "annotations": {},
      "timestamp": "0"
    },
    {
      "line": "Got the reelers out",
      "annotations": {},
      "timestamp": "0"
    },
    {
      "line": "This ain’t no comeback",
      "annotations": {},
      "timestamp": "0"
    },
    {
      "line": "Got the realest out",
      "annotations": {},
      "timestamp": "0"
    },
    {
      "line": "",
      "annotations": {},
      "timestamp": "0"
    },
    {
      "line": "[Outro]",
      "annotations": {},
      "timestamp": "0"
    },
    {
      "line": "Soothing prose",
      "annotations": {},
      "timestamp": "0"
    },
    {
      "line": "Had some of those",
      "annotations": {},
      "timestamp": "0"
    },
    {
      "line": "Hitting notes",
      "annotations": {},
      "timestamp": "0"
    },
    {
      "line": "Couple those",
      "annotations": {},
      "timestamp": "0"
    },
    {
      "line": "Soothing prose",
      "annotations": {},
      "timestamp": "0"
    },
    {
      "line": "Had some of those",
      "annotations": {},
      "timestamp": "0"
    },
    {
      "line": "Hidden gnomes",
      "annotations": {},
      "timestamp": "0"
    },
    {
      "line": "Water those",
      "annotations": {},
      "timestamp": "0"
    },
    {
      "line": "Oh oh",
      "annotations": {},
      "timestamp": "0"
    },
    {
      "line": "I see",
      "annotations": {},
      "timestamp": "0"
    },
    {
      "line": "My sea",
      "annotations": {},
      "timestamp": "0"
    },
    {
      "line": "Saw my I ams",
      "annotations": {},
      "timestamp": "0"
    }
  ]
}