{
  "lyrics": [
    {
      "line": "",
      "annotations": {}
    },
    {
      "line": "[Intro]",
      "annotations": {
        "Intro": "Annotation for [Intro]"
      }
    },
    {
      "line": "Fresh boy chilling",
      "annotations": {}
    },
    {
      "line": "Oh oh oh oh",
      "annotations": {}
    },
    {
      "line": "",
      "annotations": {}
    },
    {
      "line": "[Chorus]",
      "annotations": {
        "Chorus": "Annotation for [Chorus]"
      }
    },
    {
      "line": "Scripting tweezers",
      "annotations": {}
    },
    {
      "line": "Applish feverish",
      "annotations": {}
    },
    {
      "line": "Ambling in nix",
      "annotations": {}
    },
    {
      "line": "Hackling in the peevish",
      "annotations": {}
    },
    {
      "line": "Scripting tweezers",
      "annotations": {}
    },
    {
      "line": "Applish feverish",
      "annotations": {}
    },
    {
      "line": "Ambling in nix",
      "annotations": {}
    },
    {
      "line": "Hackling in the peevish",
      "annotations": {}
    },
    {
      "line": "",
      "annotations": {}
    },
    {
      "line": "[Bridge]",
      "annotations": {
        "Bridge": "Annotation for [Bridge]"
      }
    },
    {
      "line": "I get the runtime",
      "annotations": {}
    },
    {
      "line": "You get the uptime",
      "annotations": {}
    },
    {
      "line": "Making up for downtimes",
      "annotations": {}
    },
    {
      "line": "I can not pr nounce frowns",
      "annotations": {}
    },
    {
      "line": "I met you at the hem of mayhem",
      "annotations": {}
    },
    {
      "line": "Car park with a backdrop fleeting",
      "annotations": {}
    },
    {
      "line": "",
      "annotations": {}
    },
    {
      "line": "[Verse 1]",
      "annotations": {
        "1": "Annotation for 1]",
        "Verse": "Annotation for [Verse"
      }
    },
    {
      "line": "I think it’s freeing",
      "annotations": {}
    },
    {
      "line": "I make me feel so feverish",
      "annotations": {}
    },
    {
      "line": "I can’t fill in on a nap on no one",
      "annotations": {}
    },
    {
      "line": "Oh woah",
      "annotations": {}
    },
    {
      "line": "",
      "annotations": {}
    },
    {
      "line": "[Bridge]",
      "annotations": {
        "Bridge": "Annotation for [Bridge]"
      }
    },
    {
      "line": "I get the runtime",
      "annotations": {}
    },
    {
      "line": "You get the uptime",
      "annotations": {}
    },
    {
      "line": "Making up for downtimes",
      "annotations": {}
    },
    {
      "line": "I can not pr nounce my frowns",
      "annotations": {}
    },
    {
      "line": "I met you at the hem of mayhem",
      "annotations": {}
    },
    {
      "line": "Car park with a backdrop fleeting",
      "annotations": {}
    },
    {
      "line": "",
      "annotations": {}
    },
    {
      "line": "[Chorus]",
      "annotations": {
        "Chorus": "Annotation for [Chorus]"
      }
    },
    {
      "line": "Scripting tweezers",
      "annotations": {}
    },
    {
      "line": "Applish feverish",
      "annotations": {}
    },
    {
      "line": "Ambling in nix",
      "annotations": {}
    },
    {
      "line": "Hackling in the peevish",
      "annotations": {}
    },
    {
      "line": "Scripting tweezers",
      "annotations": {}
    },
    {
      "line": "Applish feverish",
      "annotations": {}
    },
    {
      "line": "Ambling in nix",
      "annotations": {}
    },
    {
      "line": "Hackling in the peevish",
      "annotations": {}
    },
    {
      "line": "",
      "annotations": {}
    },
    {
      "line": "[Verse 2]",
      "annotations": {
        "2": "Annotation for 2]",
        "Verse": "Annotation for [Verse"
      }
    },
    {
      "line": "Wishing on a fetter falling in place",
      "annotations": {}
    },
    {
      "line": "Quizzing our affair, i fear it’s you, you",
      "annotations": {}
    },
    {
      "line": "Hopping undercover",
      "annotations": {}
    },
    {
      "line": "(hopping undercover)",
      "annotations": {}
    },
    {
      "line": "Looking for what other",
      "annotations": {}
    },
    {
      "line": "(looking for what other)",
      "annotations": {}
    },
    {
      "line": "Now i’m wishing, and i’m pacing",
      "annotations": {}
    },
    {
      "line": "And i’m dancing with my heart",
      "annotations": {}
    },
    {
      "line": "Looking for her fault",
      "annotations": {}
    },
    {
      "line": "I think i’ll finally afford her",
      "annotations": {}
    },
    {
      "line": "I’ve been dancing, i’ve been calling",
      "annotations": {}
    },
    {
      "line": "Looking for it, her heart linked to another",
      "annotations": {}
    },
    {
      "line": "",
      "annotations": {}
    },
    {
      "line": "[Chorus]",
      "annotations": {
        "Chorus": "Annotation for [Chorus]"
      }
    },
    {
      "line": "Scripting tweezers",
      "annotations": {}
    },
    {
      "line": "Applish feverish",
      "annotations": {}
    },
    {
      "line": "Ambling in nix",
      "annotations": {}
    },
    {
      "line": "Hackling in the peevish",
      "annotations": {}
    },
    {
      "line": "Scripting tweezers",
      "annotations": {}
    },
    {
      "line": "Applish feverish",
      "annotations": {}
    },
    {
      "line": "Ambling in nix",
      "annotations": {}
    },
    {
      "line": "Hackling in the peevish",
      "annotations": {}
    },
    {
      "line": "",
      "annotations": {}
    },
    {
      "line": "[Verse 3]",
      "annotations": {
        "3": "Annotation for 3]",
        "Verse": "Annotation for [Verse"
      }
    },
    {
      "line": "My problems dress the same",
      "annotations": {}
    },
    {
      "line": "Looking for whodunit hey",
      "annotations": {}
    },
    {
      "line": "Think i might be a crescent",
      "annotations": {}
    },
    {
      "line": "Looking like he’s gonna paint",
      "annotations": {}
    },
    {
      "line": "What’s your name",
      "annotations": {}
    },
    {
      "line": "Her k!ll will say",
      "annotations": {}
    },
    {
      "line": "I’ll fade away with leaves",
      "annotations": {}
    },
    {
      "line": "Fade away with leaves",
      "annotations": {}
    },
    {
      "line": "D mn it, another day comes",
      "annotations": {}
    },
    {
      "line": "Fade away with leaves",
      "annotations": {}
    }
  ]
}