{
  "lyrics": [
    {
      "line": "",
      "annotations": {}
    },
    {
      "line": "[Verse 1]",
      "annotations": {
        "1": "Annotation for 1]",
        "Verse": "Annotation for [Verse"
      }
    },
    {
      "line": "Sometimes i wish i was a reusable bag",
      "annotations": {}
    },
    {
      "line": "So my bidding back",
      "annotations": {}
    },
    {
      "line": "I don’t want to be that little man",
      "annotations": {}
    },
    {
      "line": "Who never stands",
      "annotations": {}
    },
    {
      "line": "",
      "annotations": {}
    },
    {
      "line": "[Bridge]",
      "annotations": {
        "Bridge": "Annotation for [Bridge]"
      }
    },
    {
      "line": "Burr on who i am",
      "annotations": {}
    },
    {
      "line": "Who i used to be",
      "annotations": {}
    },
    {
      "line": "How long ‘fore i get the whisk",
      "annotations": {}
    },
    {
      "line": "Hit the mental bin",
      "annotations": {}
    },
    {
      "line": "Right we can all see",
      "annotations": {}
    },
    {
      "line": "The turret clock cl!ck",
      "annotations": {}
    },
    {
      "line": "Hail your fl!ck",
      "annotations": {}
    },
    {
      "line": "",
      "annotations": {}
    },
    {
      "line": "[Chorus]",
      "annotations": {
        "Chorus": "Annotation for [Chorus]"
      }
    },
    {
      "line": "Knocking off insouciant",
      "annotations": {}
    },
    {
      "line": "All i ever want is you",
      "annotations": {}
    },
    {
      "line": "All i ever don’t get is you",
      "annotations": {}
    },
    {
      "line": "Knocking off insouciant",
      "annotations": {}
    },
    {
      "line": "All i ever want is you",
      "annotations": {}
    },
    {
      "line": "All i ever don’t get is you",
      "annotations": {}
    },
    {
      "line": "",
      "annotations": {}
    },
    {
      "line": "[Verse 2]",
      "annotations": {
        "2": "Annotation for 2]",
        "Verse": "Annotation for [Verse"
      }
    },
    {
      "line": "D mn i’m back",
      "annotations": {}
    },
    {
      "line": "To her park",
      "annotations": {}
    },
    {
      "line": "It’s not right",
      "annotations": {}
    },
    {
      "line": "If it don’t hit the spot",
      "annotations": {}
    },
    {
      "line": "You should let me know",
      "annotations": {}
    },
    {
      "line": "Why the gourmet revolves the core rim",
      "annotations": {}
    },
    {
      "line": "Marinate you all day",
      "annotations": {}
    },
    {
      "line": "Soots don’t heal your love",
      "annotations": {}
    },
    {
      "line": "",
      "annotations": {}
    },
    {
      "line": "[Bridge]",
      "annotations": {
        "Bridge": "Annotation for [Bridge]"
      }
    },
    {
      "line": "Burr on who i am",
      "annotations": {}
    },
    {
      "line": "Who i used to bе",
      "annotations": {}
    },
    {
      "line": "How long ‘fore i get the whisk",
      "annotations": {}
    },
    {
      "line": "Hit thе mental bin",
      "annotations": {}
    },
    {
      "line": "Right we can all see",
      "annotations": {}
    },
    {
      "line": "The turret clock cl!ck",
      "annotations": {}
    },
    {
      "line": "Hail your fl!ck",
      "annotations": {}
    },
    {
      "line": "",
      "annotations": {}
    },
    {
      "line": "[Chorus]",
      "annotations": {
        "Chorus": "Annotation for [Chorus]"
      }
    },
    {
      "line": "Knocking off insouciant",
      "annotations": {}
    },
    {
      "line": "All i ever want is you",
      "annotations": {}
    },
    {
      "line": "All i ever don’t get is you",
      "annotations": {}
    },
    {
      "line": "Knocking off insouciant",
      "annotations": {}
    },
    {
      "line": "All i ever want is you",
      "annotations": {}
    },
    {
      "line": "All i ever don’t get is you",
      "annotations": {}
    },
    {
      "line": "",
      "annotations": {}
    },
    {
      "line": "[Outro]",
      "annotations": {
        "Outro": "Annotation for [Outro]"
      }
    },
    {
      "line": "Sometimes i wish i was a reusable bag",
      "annotations": {}
    },
    {
      "line": "So my bidding back",
      "annotations": {}
    },
    {
      "line": "I don’t want to be that little man",
      "annotations": {}
    },
    {
      "line": "Who never stands",
      "annotations": {}
    }
  ]
}